[{
  "_id": {
    "$oid": "5ede136a39fc14347287ccdd"
  },
  "name": "Digestive",
  "img": "https://imagesvc.meredithcorp.io/v3/mm/image?q=85&c=sc&poi=face&url=https%3A%2F%2Fimg1.cookinglight.timeinc.net%2Fsites%2Fdefault%2Ffiles%2Fstyles%2F4_3_horizontal_-_1200x900%2Fpublic%2F1548352137%2Figestive-cookies.jpg%3Fitok%3DuuN2sNiL",
  "RDT": 5,
  "winratio": 0,
  "comparisoncount": 0,
  "wincount": 0
},{
  "_id": {
    "$oid": "5ede139a39fc14347287ccde"
  },
  "name": "Hobnob",
  "img": "https://upload.wikimedia.org/wikipedia/commons/9/95/Hobnobs.jpg",
  "RDT": 5,
  "winratio": 0,
  "comparisoncount": 0,
  "wincount": 0
},{
  "_id": {
    "$oid": "5ede13e039fc14347287ccdf"
  },
  "name": "Malted Milk",
  "img": "https://media.timeout.com/images/102872476/image.jpg",
  "RDT": 6,
  "winratio": 0,
  "comparisoncount": 0,
  "wincount": 0
},{
  "_id": {
    "$oid": "5ede13eb39fc14347287cce0"
  },
  "name": "Ginger Nut",
  "img": "https://peasepudding.files.wordpress.com/2010/05/gingernut.jpg",
  "RDT": 3,
  "winratio": 0,
  "comparisoncount": 0,
  "wincount": 0
},{
  "_id": {
    "$oid": "5ede13f739fc14347287cce1"
  },
  "name": "Fig Roll",
  "img": "https://bakingfanatic.files.wordpress.com/2019/08/fig-rose-and-pistachio-rolls-3.jpg?w=1093",
  "RDT": 4,
  "winratio": 0,
  "comparisoncount": 0,
  "wincount": 0
},{
  "_id": {
    "$oid": "5ede140439fc14347287cce2"
  },
  "name": "Chocolate Digestive",
  "img": "https://www.telegraph.co.uk/content/dam/food-and-drink/2016/05/26/5_Chocolate_Hobnob_trans_NvBQzQNjv4BqqVzuuqpFlyLIwiB6NTmJwfSVWeZ_vEN7c6bHu2jJnT8.jpg?imwidth=450",
  "RDT": 4,
  "winratio": 0,
  "comparisoncount": 0,
  "wincount": 0
},{
  "_id": {
    "$oid": "5ede141439fc14347287cce3"
  },
  "name": "Chocolate Hobnob",
  "img": "https://dowerandhollingsworth.files.wordpress.com/2016/07/img_2759.jpg",
  "RDT": 9,
  "winratio": 0,
  "comparisoncount": 0,
  "wincount": 0
},{
  "_id": {
    "$oid": "5ede141e39fc14347287cce4"
  },
  "name": "Rich Tea",
  "img": "https://i.pinimg.com/originals/c7/4c/dd/c74cddd3548f420597a478c457a83a54.jpg",
  "RDT": 4,
  "winratio": 0,
  "comparisoncount": 0,
  "wincount": 0
},{
  "_id": {
    "$oid": "5ede142739fc14347287cce5"
  },
  "name": "Custard Cream",
  "img": "https://d11fdyfhxcs9cr.cloudfront.net/templates/184807/myimages/custard_cream_1.jpg",
  "RDT": 8,
  "winratio": 0,
  "comparisoncount": 0,
  "wincount": 0
},{
  "_id": {
    "$oid": "5ede143439fc14347287cce6"
  },
  "name": "Jammy Dodger",
  "img": "https://dqzrr9k4bjpzk.cloudfront.net/images/14403044/1227758549.jpg",
  "RDT": 8,
  "winratio": 0,
  "comparisoncount": 0,
  "wincount": 0
},{
  "_id": {
    "$oid": "5ede143f39fc14347287cce7"
  },
  "name": "Shortbread",
  "img": "https://media.irishpost.co.uk/uploads/2020/03/30161636/shortbread-irish-post.jpg",
  "RDT": 11,
  "winratio": 0,
  "comparisoncount": 0,
  "wincount": 0
},{
  "_id": {
    "$oid": "5ede144839fc14347287cce8"
  },
  "name": "Bourbon",
  "img": "https://nitrocdn.com/AqOsDSWHlMyaklhBnvzkgRREKBfEHKZc/assets/static/source/rev-b494b1d/wp-content/uploads/2017/10/fullsizeoutput_6b2a-1024x683.jpeg",
  "RDT": 7,
  "winratio": 0,
  "comparisoncount": 0,
  "wincount": 0
},{
  "_id": {
    "$oid": "5ede145339fc14347287cce9"
  },
  "name": "Oreo",
  "img": "https://theorganisedhousewife.com.au/wp-content/uploads/2011/07/oreo-biscuit-recipe-cookie.jpg",
  "RDT": 3,
  "winratio": 0,
  "comparisoncount": 0,
  "wincount": 0
},{
  "_id": {
    "$oid": "5ede145c39fc14347287ccea"
  },
  "name": "Nice",
  "img": "https://i2.wp.com/nibblemybiscuit.com/wp-content/uploads/2017/03/NICE-BISCUITS.jpg?fit=389%2C272&ssl=1",
  "RDT": 4,
  "winratio": 0,
  "comparisoncount": 0,
  "wincount": 0
},{
  "_id": {
    "$oid": "5ede146439fc14347287cceb"
  },
  "name": "Party Ring",
  "img": "https://slummysinglemummy.com/wp-content/uploads/2018/04/DSC_0054.jpg",
  "RDT": 5,
  "winratio": 0,
  "comparisoncount": 0,
  "wincount": 0
},{
  "_id": {
    "$oid": "5ede146c39fc14347287ccec"
  },
  "name": "Garibaldi",
  "img": "https://weebirdiecafe.files.wordpress.com/2015/02/p1100439-2.jpg",
  "RDT": 5,
  "winratio": 0,
  "comparisoncount": 0,
  "wincount": 0
},{
  "_id": {
    "$oid": "5ede147639fc14347287cced"
  },
  "name": "Choc Chip Cookie",
  "img": "https://pediaa.com/wp-content/uploads/2015/12/Difference-Between-Cookies-and-Biscuits-image-1-1024x680.jpg",
  "RDT": 6,
  "winratio": 0,
  "comparisoncount": 0,
  "wincount": 0
}]